[{"name":"manas","comment":"shukla","rating":"4"},{"name":"goldi","comment":"Shukla Bukla","rating":"2"},{"name":"mansi","comment":"jndkjvnkdsnvldfkmvlkdmflkvmlkdfmvlkmdflkvmkldfmvklmdfkvmkldfmvklmdfkvmkd","rating":"5"},{"name":"test","comment":"test","rating":"3"},{"name":"manas","comment":"working","rating":"3"},{"name":"Platinum","comment":"Nice","rating":"5"},{"name":"Platu","comment":"Nice Website Nice WebsiteNice WebsiteNice WebsiteNice WebsiteNice WebsiteNice WebsiteNice WebsiteNice WebsiteNice WebsiteNice WebsiteNice WebsiteNice WebsiteNice WebsiteNice WebsiteNice WebsiteNice WebsiteNice WebsiteNice WebsiteNice WebsiteNice WebsiteNice WebsiteNice WebsiteNice WebsiteNice WebsiteNice WebsiteNice WebsiteNice WebsiteNice WebsiteNice Website","rating":""},{"name":"Ranu","comment":"Rasgulla khana h","rating":"5"},{"name":"paginator","comment":"kaisa h?","rating":"5"}]